{
  "id": "2b3f980c2e7dbc",
  "name": "luizz",
  "username": "lluiz",
  "email": "ll@hotmail.com",
  "emailConfirmation": "ll@hotmail.com",
  "phone": "1188888",
  "password": "$2b$10$aDfwSh1ZpWbaRGQPQmFKiOniehnVIDegLvaJ9q7Rtj5y0DxK8.I6e",
  "passwordConfirmation": "$2b$10$dHys74MoLJwMdLMKwPjK8.Ls3ynEM41arCB5kHNtG0s3ZUaWH/KaO",
  "bioUpdate": "sljndlaksndsa",
  "avatar": {
    "fieldname": "avatar",
    "originalname": "Captura de Tela 2021-12-09 às 00.40.21.png",
    "encoding": "7bit",
    "mimetype": "image/png",
    "destination": "public/uploads/",
    "filename": "Captura de Tela 2021-12-09 às 00.40.21.png",
    "path": "public/uploads/Captura de Tela 2021-12-09 às 00.40.21.png",
    "size": 3977
  }
}